{
  "rpc-reply":{
    "-xmlns":"urn:ietf:params:xml:ns:netconf:base:1.0",
    "-message-id":"2",
    "meta":{
      "-xmlns":"urn:ietf:params:xml:ns:yang:alto-service",
      "cost-types":[
        {
          "cost-type-name":"num-routing",
          "cost-mode":"numerical",
          "cost-metric":"routingcost",
          "description":"My default"
        },
        {
          "cost-type-name":"num-hop",
          "cost-mode":"numerical",
          "cost-metric":"hopcount"
        },
        {
          "cost-type-name":"ord-routing",
          "cost-mode":"ordinal",
          "cost-metric":"routingcost"
        },
        {
          "cost-type-name":"ord-hop",
          "cost-mode":"ordinal",
          "cost-metric":"hopcount"
        }
      ],
      "default-alto-network-map":"my-default-network-map"
    },
    "resources":[
      {
        "-xmlns":"urn:ietf:params:xml:ns:yang:alto-service",
        "resource-id":"filtered-network-map",
        "uri":"http://custom.alto.example.com/networkmap/filtered",
        "media-type":"application/alto-networkmap+json",
        "accepts":"application/alto-networkmapfilter+json",
        "uses":[
          "my-default-network-map"
        ]
      },
      {
        "-xmlns":"urn:ietf:params:xml:ns:yang:alto-service",
        "resource-id":"filtered-cost-map",
        "uri":"http://custom.alto.example.com/costmap/filtered",
        "media-type":"application/alto-costmap+json",
        "accepts":"application/alto-costmapfilter+json",
        "capabilities":{
          "cost-constraints":true,
          "cost-type-names":[
            "num-routing",
            "num-hop",
            "ord-routing",
            "ord-hop"
          ]
        },
        "uses":[
          "my-default-network-map"
        ]
      },
      {
        "-xmlns":"urn:ietf:params:xml:ns:yang:alto-service",
        "resource-id":"ordinal-routing-cost-map",
        "uri":"http://custom.alto.example.com/ord/routingcost",
        "media-type":"application/alto-costmap+json",
        "capabilities":{
          "cost-type-names":[
            "ord-routing"
          ]
        },
        "uses":[
          "my-default-network-map"
        ]
      },
      {
        "-xmlns":"urn:ietf:params:xml:ns:yang:alto-service",
        "resource-id":"ordinal-hopcount-cost-map",
        "uri":"http://custom.alto.example.com/ord/hopcount",
        "media-type":"application/alto-costmap+json",
        "capabilities":{
          "cost-type-names":[
            "ord-hop"
          ]
        },
        "uses":[
          "my-default-network-map"
        ]
      }
    ]
  }
}